pre_commit_html/__init__.py
pre_commit_html/__main__.py
pre_commit_html/main.py
pre_commit_html/site/nothing
pre_commit_html/site/templates/html_content.jinja
pre_commit_html/utils.py
pre_commit_html-0.1.5.dist-info/LICENSE
pre_commit_html-0.1.5.dist-info/METADATA
pre_commit_html-0.1.5.dist-info/WHEEL
pre_commit_html-0.1.5.dist-info/entry_points.txt
pre_commit_html-0.1.5.dist-info/RECORD
