Metadata-Version: 2.3
Name: pre_commit_html
Version: 0.1.5
Summary: Format results from pre-commit cmd to HTML file
License: MIT
Author: Robotz213
Author-email: nicholas@robotz.dev
Requires-Python: >=3.13,<4.0
Classifier: License :: OSI Approved :: MIT License
Classifier: Programming Language :: Python :: 3
Classifier: Programming Language :: Python :: 3.13
Requires-Dist: html2text (>=2024.2.26,<2025.0.0)
Requires-Dist: jinja2 (>=3.1.5,<4.0.0)
Requires-Dist: pre-commit (>=4.1.0,<5.0.0)
